fastpace.pypy37-pp73-x86_64-linux-gnu.so
fastpace-1.0.1.dist-info/RECORD
fastpace-1.0.1.dist-info/LICENSE
fastpace-1.0.1.dist-info/top_level.txt
fastpace-1.0.1.dist-info/WHEEL
fastpace-1.0.1.dist-info/METADATA
