Metadata-Version: 2.1
Name: fastpace
Version: 1.0.1
Summary: FaSTPACE: A Fast and Scalable Tool for Peptide Alignment and Consensus Extraction
Home-page: https://github.com/hkotb/fastpace
Author: Hazem M. Kotb
Author-email: hazem.mamdouh.kotb@gmail.com
Classifier: Programming Language :: Python :: 3
Classifier: License :: OSI Approved :: MIT License
Classifier: Operating System :: OS Independent
License-File: LICENSE
